{
	"hero": {
		"now": {
			"title": "你好, 我是 Sebastian",
			"intro": "我目前作为一位国民服役人员 (NSF) 在新加坡的国防数码防卫与情报军部队 (DIS)。我爱学习与尝试有趣的事物。",
			"past": "我曾参与型项目, 为社区做出贡献。",
			"hobbies": "我喜欢和朋友一起玩电子游戏, 有时也会阅读书籍。"
		},
		"social": {
			"github": "https://github.com/SebassNoob",
			"linkedin": "https://www.linkedin.com/in/sebastian-ong-978a73307/",
			"email": "mailto:sebastian.ong@hotmail.com",
			"blog": "https://blog.sebassnoob.dev"
		}
	},
	"experiences": {
		"title": "经历",
		"subtitle": "以下是我曾参与过的项目！",
		"content": [
			{
				"title": "顾问开发者",
				"entity": "The Signpost Project",
				"entityUrl": "https://www.thesignpostproject.org/",
				"startDate": "2023年6月",
				"endDate": "至今",
				"descriptionPoints": [
					"制作了一个网页应用程序 (Next.js + Nest.js, 使用 Turborepo), 帮助组织管理内部数据, 减少200%的云端费用, 并改进数据访问控制。",
					"每周在 3 个社区做志愿工作, 帮助本地纸巾销售者解决个人问题。"
				]
			},
			{
				"title": "学生",
				"entity": "莱佛士书院 (Raffles Institution)",
				"entityUrl": "https://www.ri.edu.sg/",
				"startDate": "2023年2月",
				"endDate": "2024年11月",
				"descriptionPoints": [
					"取得 GCE A 水准证书: H2 计算机科学、H2 经济学、H2 数学、H2 物理、H1 普通论文、H1 项目工作。",
					"活跃于学校的 Interact Club: 每周在国家肾脏基金会 (National Kidney Foundation) 做志愿者, 每两周指导小学生, 参与倡导活动。",
					"制作了 OneInteract, 一个用于管理考勤的网页应用程序 (Next.js + Express), 并用于管理 120+ 名学校志愿者。",
					"参与黑客马拉松和 CTF 竞赛: BuildingBlocs 2023年9月 (冠军); Whitehacks 2024 (第五名)。"
				]
			},
			{
				"title": "开发者",
				"entity": "Holy Grail",
				"entityUrl": "https://grail.moe",
				"startDate": "2023年6月",
				"endDate": "2023年12月",
				"descriptionPoints": [
					"参与 Holy Grail 项目的开发, 一个用于新加坡考试资料众包的网页应用程序 (Vite + FastAPI)。这程序拥有 2000+ 活跃用户, 日均请求量达 14000 次。",
					"合并了 20 多个 pull request, 并构建了多个新功能: 用户设置、文件批量上传, 用户界面改进。"
				]
			},
			{
				"title": "学生",
				"entity": "南华中学 (Nan Hua High School)",
				"entityUrl": "https://nanhuahigh.moe.edu.sg/",
				"startDate": "2019年1月",
				"endDate": "2022年11月",
				"descriptionPoints": [
					"取得 GCE O 水准证书: 英文、综合人文学科 (地理/社会研究)、数学、高级数学、物理、化学、高级华文、马来文 (特选课程)。"
				]
			}
		]
	}
}
